intellibot/__init__.py
intellibot/api.py
intellibot/cli.py
intellibot-0.5.dist-info/LICENSE
intellibot-0.5.dist-info/METADATA
intellibot-0.5.dist-info/WHEEL
intellibot-0.5.dist-info/entry_points.txt
intellibot-0.5.dist-info/top_level.txt
intellibot-0.5.dist-info/RECORD
