Metadata-Version: 2.1
Name: intellibot
Version: 0.5
Summary: A CLI tool for interacting with intellibot API
Home-page: https://github.com/PinsaraPerera/intellihack_research_agent.git
Author: Pawan Pinsara
Author-email: 1pawanpinsara@gmail.com
Classifier: Programming Language :: Python :: 3
Classifier: License :: OSI Approved :: Apache Software License
Classifier: Operating System :: OS Independent
Requires-Python: >=3.6
License-File: LICENSE
Requires-Dist: click
Requires-Dist: requests
Requires-Dist: colorama
